summ_eval/__init__.py
summ_eval/bert_score_metric.py
summ_eval/blanc_metric.py
summ_eval/bleu_metric.py
summ_eval/calc_scores.py
summ_eval/chrfpp_metric.py
summ_eval/cider_metric.py
summ_eval/cider_utils.py
summ_eval/data_stats_metric.py
summ_eval/data_stats_utils.py
summ_eval/meteor_metric.py
summ_eval/metric.py
summ_eval/mover_score_metric.py
summ_eval/rouge_metric.py
summ_eval/rouge_we_metric.py
summ_eval/s3_metric.py
summ_eval/s3_utils.py
summ_eval/sentence_movers_metric.py
summ_eval/sentence_movers_utils.py
summ_eval/summa_qa_metric.py
summ_eval/summa_qa_utils.py
summ_eval/supert_metric.py
summ_eval/supert_utils.py
summ_eval/syntactic_metric.py
summ_eval/syntactic_utils.py
summ_eval/test_util.py
summ_eval/sentence_transformers/LoggingHandler.py
summ_eval/sentence_transformers/SentenceTransformer.py
summ_eval/sentence_transformers/__init__.py
summ_eval/sentence_transformers/data_samplers.py
summ_eval/sentence_transformers/datasets.py
summ_eval/sentence_transformers/util.py
summ_eval/sentence_transformers/evaluation/BinaryEmbeddingSimilarityEvaluator.py
summ_eval/sentence_transformers/evaluation/EmbeddingSimilarityEvaluator.py
summ_eval/sentence_transformers/evaluation/LabelAccuracyEvaluator.py
summ_eval/sentence_transformers/evaluation/SentenceEvaluator.py
summ_eval/sentence_transformers/evaluation/SequentialEvaluator.py
summ_eval/sentence_transformers/evaluation/SimilarityFunction.py
summ_eval/sentence_transformers/evaluation/TripletEvaluator.py
summ_eval/sentence_transformers/evaluation/__init__.py
summ_eval/sentence_transformers/losses/BatchHardTripletLoss.py
summ_eval/sentence_transformers/losses/CosineSimilarityLoss.py
summ_eval/sentence_transformers/losses/MultipleNegativesRankingLoss.py
summ_eval/sentence_transformers/losses/SoftmaxLoss.py
summ_eval/sentence_transformers/losses/TripletLoss.py
summ_eval/sentence_transformers/losses/__init__.py
summ_eval/sentence_transformers/losses/test_batch_hard_triplet_loss.py
summ_eval-0.892.dist-info/METADATA
summ_eval-0.892.dist-info/WHEEL
summ_eval-0.892.dist-info/entry_points.txt
summ_eval-0.892.dist-info/top_level.txt
summ_eval-0.892.dist-info/RECORD
