Metadata-Version: 2.1
Name: summ-eval
Version: 0.892
Summary: Toolkit for summarization evaluation
Home-page: https://github.com/Yale-LILY/SummEval
Author: Alex Fabbri, Wojciech Kryściński
Author-email: alexander.fabbri@yale.edu, wojciech.kryscinski@salesforce.com
License: MIT
Platform: UNKNOWN
Requires-Dist: bert-score
Requires-Dist: gin-config
Requires-Dist: moverscore
Requires-Dist: pytorch-pretrained-bert
Requires-Dist: psutil
Requires-Dist: six
Requires-Dist: numpy (>=1.11.0)
Requires-Dist: stanza
Requires-Dist: sacremoses
Requires-Dist: transformers (>=2.2.0)
Requires-Dist: spacy (>=2.2.0)
Requires-Dist: sacrebleu
Requires-Dist: pyemd (==0.5.1)
Requires-Dist: click
Requires-Dist: nltk
Requires-Dist: cython
Requires-Dist: scipy
Requires-Dist: networkx
Requires-Dist: blanc
